[
    {
    "ROLLNO": "1",
    "NAME": "SHAIKH ADIL",
    "FACULTY": "SCIENCE",
    "SUBJECT1": "English",
    "MARK1": "87",
    "SUBJECT2": "Arabic",
    "MARK2": "79",
    "SUBJECT3": "Physics",
    "MARK3": "80",
    "SUBJECT4": "Chemistry",
    "MARK4": "88",
    "SUBJECT5": "Maths",
    "MARK5": "92",
    "SUBJECT6": "Biology",
    "MARK6": "90",
    "SUBJECT7": "EVS",
    "MARK7": "A",
    "SUBJECT8": "Phy.Edn.",
    "MARK8": "A",
    "TOTAL": "516.00",
    "PERCENTAGE": "86.00",
    "REMARK": "PASS"
    },
    {
    "ROLLNO": "2",
    "NAME": "KAIF AKHTAR",
    "FACULTY": "SCIENCE",
    "SUBJECT1": "English",
    "MARK1": "83",
    "SUBJECT2": "Hindi",
    "MARK2": "78",
    "SUBJECT3": "Physics",
    "MARK3": "87",
    "SUBJECT4": "Chemistry",
    "MARK4": "83",
    "SUBJECT5": "Maths",
    "MARK5": "85",
    "SUBJECT6": "Biology",
    "MARK6": "80",
    "SUBJECT7": "EVS",
    "MARK7": "A",
    "SUBJECT8": "Phy.Edn.",
    "MARK8": "A",
    "TOTAL": "496.00",
    "PERCENTAGE": "82.66",
    "REMARK": "PASS"
    },
    {
    "ROLLNO": "3",
    "NAME": "FAHAD QURESHI",
    "FACULTY": "SCIENCE",
    "SUBJECT1": "English",
    "MARK1": "78",
    "SUBJECT2": "Arabic",
    "MARK2": "88",
    "SUBJECT3": "Physics",
    "MARK3": "89",
    "SUBJECT4": "Chemistry",
    "MARK4": "76",
    "SUBJECT5": "Maths",
    "MARK5": "80",
    "SUBJECT6": "Biology",
    "MARK6": "76",
    "SUBJECT7": "EVS",
    "MARK7": "A",
    "SUBJECT8": "Phy.Edn.",
    "MARK8": "A",
    "TOTAL": "487.00",
    "PERCENTAGE": "81.16",
    "REMARK": "PASS"
    },
    {
    "ROLLNO": "4",
    "NAME": "SHAIZAAN MOHAMMAD",
    "FACULTY": "SCIENCE",
    "SUBJECT1": "English",
    "MARK1": "77",
    "SUBJECT2": "Marathi",
    "MARK2": "68",
    "SUBJECT3": "Physics",
    "MARK3": "77",
    "SUBJECT4": "Chemistry",
    "MARK4": "74",
    "SUBJECT5": "Maths",
    "MARK5": "76",
    "SUBJECT6": "Biology",
    "MARK6": "67",
    "SUBJECT7": "EVS",
    "MARK7": "A",
    "SUBJECT8": "Phy.Edn.",
    "MARK8": "A",
    "TOTAL": "439.00",
    "PERCENTAGE": "73.16",
    "REMARK": "PASS"
    },
    {
    "ROLLNO": "5",
    "NAME": "FAISAL QURESHI",
    "FACULTY": "SCIENCE",
    "SUBJECT1": "English",
    "MARK1": "77",
    "SUBJECT2": "Urdu",
    "MARK2": "77",
    "SUBJECT3": "Physics",
    "MARK3": "77",
    "SUBJECT4": "Chemistry",
    "MARK4": "69",
    "SUBJECT5": "Maths",
    "MARK5": "72",
    "SUBJECT6": "Biology",
    "MARK6": "72",
    "SUBJECT7": "EVS",
    "MARK7": "A",
    "SUBJECT8": "Phy.Edn.",
    "MARK8": "A",
    "TOTAL": "444.00",
    "PERCENTAGE": "74",
    "REMARK": "PASS"
    },
    {
    "ROLLNO": "1",
    "NAME": "MUKHTAR JAFRI",
    "FACULTY": "COMMERCE",
    "SUBJECT1": "English",
    "MARK1": "77",
    "SUBJECT2": "Hindi",
    "MARK2": "78",
    "SUBJECT3": "S.P.",
    "MARK3": "79",
    "SUBJECT4": "ECO",
    "MARK4": "74",
    "SUBJECT5": "OCM",
    "MARK5": "72",
    "SUBJECT6": "B.K",
    "MARK6": "73",
    "SUBJECT7": "EVS",
    "MARK7": "A",
    "SUBJECT8": "Phy.Edn.",
    "MARK8": "A",
    "TOTAL": "453.00",
    "PERCENTAGE": "75.5",
    "REMARK": "PASS"
    },
    {
    "ROLLNO": "2",
    "NAME": "SARWAR JAFRI",
    "FACULTY": "COMMERCE",
    "SUBJECT1": "English",
    "MARK1": "86",
    "SUBJECT2": "Hindi",
    "MARK2": "77",
    "SUBJECT3": "S.P.",
    "MARK3": "94",
    "SUBJECT4": "ECO",
    "MARK4": "87",
    "SUBJECT5": "OCM",
    "MARK5": "91",
    "SUBJECT6": "B.K",
    "MARK6": "84",
    "SUBJECT7": "EVS",
    "MARK7": "A",
    "SUBJECT8": "Phy.Edn.",
    "MARK8": "A",
    "TOTAL": "519.00",
    "PERCENTAGE": "86.5",
    "REMARK": "PASS"
    },
    {
    "ROLLNO": "3",
    "NAME": "MOHAMMED SHAFE",
    "FACULTY": "COMMERCE",
    "SUBJECT1": "English",
    "MARK1": "77",
    "SUBJECT2": "Arabic",
    "MARK2": "79",
    "SUBJECT3": "S.P.",
    "MARK3": "90",
    "SUBJECT4": "ECO",
    "MARK4": "82",
    "SUBJECT5": "OCM",
    "MARK5": "83",
    "SUBJECT6": "B.K",
    "MARK6": "77",
    "SUBJECT7": "EVS",
    "MARK7": "A",
    "SUBJECT8": "Phy.Edn.",
    "MARK8": "A",
    "TOTAL": "488.00",
    "PERCENTAGE": "81.33",
    "REMARK": "PASS"
    },
    {
    "ROLLNO": "4",
    "NAME": " SHAIKH SAIF",
    "FACULTY": "COMMERCE",
    "SUBJECT1": "English",
    "MARK1": "77",
    "SUBJECT2": "Urdu",
    "MARK2": "79",
    "SUBJECT3": "S.P.",
    "MARK3": "76",
    "SUBJECT4": "ECO",
    "MARK4": "78",
    "SUBJECT5": "OCM",
    "MARK5": "70",
    "SUBJECT6": "B.K",
    "MARK6": "67",
    "SUBJECT7": "EVS",
    "MARK7": "A",
    "SUBJECT8": "Phy.Edn.",
    "MARK8": "A",
    "TOTAL": "447.00",
    "PERCENTAGE": "74.5",
    "REMARK": "PASS"
    },
    {
    "ROLLNO": "5",
    "NAME": " SYED HARES",
    "FACULTY": "COMMERCE",
    "SUBJECT1": "English",
    "MARK1": "84",
    "SUBJECT2": "Marathi",
    "MARK2": "81",
    "SUBJECT3": "S.P.",
    "MARK3": "92",
    "SUBJECT4": "ECO",
    "MARK4": "85",
    "SUBJECT5": "OCM",
    "MARK5": "87",
    "SUBJECT6": "B.K",
    "MARK6": "81",
    "SUBJECT7": "EVS",
    "MARK7": "A",
    "SUBJECT8": "Phy.Edn.",
    "MARK8": "A",
    "TOTAL": "510.00",
    "PERCENTAGE": "85",
    "REMARK": "PASS"
    },
    {
    "ROLLNO": "1",
    "NAME": "HASNAIN YAR KHAN",
    "FACULTY": "ARTS",
    "SUBJECT1": "English",
    "MARK1": "77",
    "SUBJECT2": "Hindi",
    "MARK2": "68",
    "SUBJECT3": "Sociology",
    "MARK3": "77",
    "SUBJECT4": "Political Science",
    "MARK4": "69",
    "SUBJECT5": "History",
    "MARK5": "67",
    "SUBJECT6": "Psychology",
    "MARK6": "67",
    "SUBJECT7": "EVS",
    "MARK7": "A",
    "SUBJECT8": "Phy.Edn.",
    "MARK8": "A",
    "TOTAL": "425.00",
    "PERCENTAGE": "70.83",
    "REMARK": "PASS"
    },
    {
    "ROLLNO": "2",
    "NAME": " SHAIKH MOHAMMED SAAD",
    "FACULTY": "ARTS",
    "SUBJECT1": "English",
    "MARK1": "77",
    "SUBJECT2": "Arabic",
    "MARK2": "69",
    "SUBJECT3": "Sociology",
    "MARK3": "86",
    "SUBJECT4": "Political Science",
    "MARK4": "80",
    "SUBJECT5": "History",
    "MARK5": "67",
    "SUBJECT6": "Psychology",
    "MARK6": "74",
    "SUBJECT7": "EVS",
    "MARK7": "A",
    "SUBJECT8": "Phy.Edn.",
    "MARK8": "A",
    "TOTAL": "453.00",
    "PERCENTAGE": "75.5",
    "REMARK": "PASS"
    },
    {
    "ROLLNO": "3",
    "NAME": " SHAIKH KHALEEL",
    "FACULTY": "ARTS",
    "SUBJECT1": "English",
    "MARK1": "84",
    "SUBJECT2": "Urdu",
    "MARK2": "94",
    "SUBJECT3": "Sociology",
    "MARK3": "95",
    "SUBJECT4": "Political Science",
    "MARK4": "76",
    "SUBJECT5": "History",
    "MARK5": "87",
    "SUBJECT6": "Psychology",
    "MARK6": "76",
    "SUBJECT7": "EVS",
    "MARK7": "A",
    "SUBJECT8": "Phy.Edn.",
    "MARK8": "A",
    "TOTAL": "512.00",
    "PERCENTAGE": "85.33",
    "REMARK": "PASS"
    },
    {
    "ROLLNO": "4",
    "NAME": " CHOUDHARI IRSHAD",
    "FACULTY": "ARTS",
    "SUBJECT1": "English",
    "MARK1": "85",
    "SUBJECT2": "Hindi",
    "MARK2": "76",
    "SUBJECT3": "Sociology",
    "MARK3": "96",
    "SUBJECT4": "Political Science",
    "MARK4": "82",
    "SUBJECT5": "History",
    "MARK5": "87",
    "SUBJECT6": "Psychology",
    "MARK6": "78",
    "SUBJECT7": "EVS",
    "MARK7": "A",
    "SUBJECT8": "Phy.Edn.",
    "MARK8": "A",
    "TOTAL": "504.00",
    "PERCENTAGE": "84",
    "REMARK": "PASS"
    },
    {
    "ROLLNO": "5",
    "NAME": "ZEESHAN AHEMAD",
    "FACULTY": "ARTS",
    "SUBJECT1": "English",
    "MARK1": "77",
    "SUBJECT2": "Marathi",
    "MARK2": "83",
    "SUBJECT3": "Sociology",
    "MARK3": "96",
    "SUBJECT4": "Political Science",
    "MARK4": "79",
    "SUBJECT5": "History",
    "MARK5": "80",
    "SUBJECT6": "Psychology",
    "MARK6": "73",
    "SUBJECT7": "EVS",
    "MARK7": "A",
    "SUBJECT8": "Phy.Edn.",
    "MARK8": "A",
    "TOTAL": "488.00",
    "PERCENTAGE": "81.33",
    "REMARK": "PASS"
    },
    {
        "ROLLNO": "0",
        "NAME": "SYEDA MARIA SADAF",
        "FACULTY": "SCIENCE",
        "SUBJECT1": "English",
        "MARK1": "00",
        "SUBJECT2": "Hindi",
        "MARK2": "00",
        "SUBJECT3": "Physics",
        "MARK3": "00",
        "SUBJECT4": "Chemistry",
        "MARK4": "00",
        "SUBJECT5": "Maths",
        "MARK5": "00",
        "SUBJECT6": "Biology",
        "MARK6": "00",
        "SUBJECT7": "EVS",
        "MARK7": "Z",
        "SUBJECT8": "Phy.Edn.",
        "MARK8": "Z",
        "TOTAL": "210",
        "PERCENTAGE": "35.00",
        "REMARK": "Internal Marks Deke Paas Kiye Itni Baari Agli Baar Se Padh Ke Aao Paper Mein"
        }
  ]
